hourglass/layers.py
hourglass/models.py
hourglass/training.py
hourglass/data/heatmap.py
hourglass/data/metrics.py
hourglass/data/preprocessing.py
hourglass/data/transforms.py
hourglass/data/visualization.py
hourglass/utils/config.py
hourglass/utils/logging.py
tf_hourglass_networks-0.0.1.dist-info/LICENSE
tf_hourglass_networks-0.0.1.dist-info/METADATA
tf_hourglass_networks-0.0.1.dist-info/WHEEL
tf_hourglass_networks-0.0.1.dist-info/pbr.json
tf_hourglass_networks-0.0.1.dist-info/top_level.txt
tf_hourglass_networks-0.0.1.dist-info/RECORD
