Metadata-Version: 2.1
Name: tf-hourglass-networks
Version: 0.0.1
Summary: Train hourglass neural networks via tensorflow keras.
Home-page: UNKNOWN
Author: Benjamin Schmidt
Author-email: hello@benjs.de
License: Apache-2
Platform: UNKNOWN
Classifier: Operating System :: POSIX :: Linux
Classifier: Programming Language :: Python :: 3.8
Classifier: Topic :: Scientific/Engineering
Classifier: Development Status :: 4 - Beta
Classifier: Environment :: GPU :: NVIDIA CUDA
Requires-Python: >=3.8
License-File: LICENSE
Requires-Dist: tensorflow (>=2.5.0)
Requires-Dist: tensorflow-addons
Requires-Dist: numpy (<=1.19.5)
Requires-Dist: opencv-python-headless
Requires-Dist: packaging
Requires-Dist: pillow
Requires-Dist: pytest
Requires-Dist: pyyaml
Requires-Dist: wandb
